nessaws/__init__.py
nessaws/__init__.pyc
nessaws/__main__.py
nessaws/aws.py
nessaws/aws.pyc
nessaws/cli.py
nessaws/cli.pyc
nessaws/config.py
nessaws/config.pyc
nessaws/excel.py
nessaws/excel.pyc
nessaws/mailer.py
nessaws/mailer.pyc
nessaws/nessus.py
nessaws/nessus.pyc
nessaws/__pycache__/__init__.cpython-34.pyc
nessaws/__pycache__/__init__.cpython-35.pyc
nessaws/__pycache__/aws.cpython-34.pyc
nessaws/__pycache__/aws.cpython-35.pyc
nessaws/__pycache__/cli.cpython-34.pyc
nessaws/__pycache__/cli.cpython-35.pyc
nessaws/__pycache__/config.cpython-34.pyc
nessaws/__pycache__/config.cpython-35.pyc
nessaws/__pycache__/excel.cpython-34.pyc
nessaws/__pycache__/excel.cpython-35.pyc
nessaws/__pycache__/mailer.cpython-34.pyc
nessaws/__pycache__/mailer.cpython-35.pyc
nessaws/__pycache__/nessus.cpython-34.pyc
nessaws/__pycache__/nessus.cpython-35.pyc
nessaws/templates/request-template.html
nessaws/templates/template.html
nessaws-0.0.2.dist-info/DESCRIPTION.rst
nessaws-0.0.2.dist-info/METADATA
nessaws-0.0.2.dist-info/RECORD
nessaws-0.0.2.dist-info/WHEEL
nessaws-0.0.2.dist-info/entry_points.txt
nessaws-0.0.2.dist-info/metadata.json
nessaws-0.0.2.dist-info/top_level.txt
