Metadata-Version: 2.0
Name: nessaws
Version: 0.0.2
Summary: nessaws: Automate Nessus scans against AWS EC2/RDS endpoints.
Home-page: https://github.com/TerbiumLabs/nessaws
Author: Terbium Labs
Author-email: infrastructure@terbiumlabs.com
License: UNKNOWN
Platform: UNKNOWN
Classifier: Development Status :: 2 - Pre-Alpha
Classifier: Environment :: Console
Classifier: Intended Audience :: Developers
Classifier: License :: OSI Approved :: GNU General Public License v3 (GPLv3)
Classifier: Operating System :: MacOS
Classifier: Operating System :: Microsoft :: Windows
Classifier: Operating System :: POSIX :: Linux
Classifier: Operating System :: Unix
Classifier: Programming Language :: Python :: 2
Classifier: Programming Language :: Python :: 2.7
Classifier: Programming Language :: Python :: 3
Classifier: Programming Language :: Python :: 3.3
Classifier: Programming Language :: Python :: 3.4
Classifier: Programming Language :: Python :: 3.5
Classifier: Programming Language :: Python :: 3.6
Classifier: Programming Language :: Python :: Implementation :: PyPy
Classifier: Programming Language :: Python
Classifier: Topic :: Software Development :: Libraries :: Python Modules
Classifier: Topic :: Software Development :: Libraries
Classifier: Topic :: Utilities
Requires-Dist: PyYAML
Requires-Dist: boto3 (>=1.4.4)
Requires-Dist: botocore
Requires-Dist: click
Requires-Dist: colander
Requires-Dist: colander-tools
Requires-Dist: docutils
Requires-Dist: et-xmlfile
Requires-Dist: future
Requires-Dist: futures
Requires-Dist: iso8601
Requires-Dist: jdcal
Requires-Dist: jmespath
Requires-Dist: netaddr
Requires-Dist: openpyxl
Requires-Dist: progress
Requires-Dist: python-dateutil
Requires-Dist: python-slugify
Requires-Dist: pytz
Requires-Dist: requests
Requires-Dist: s3transfer
Requires-Dist: six
Requires-Dist: translationstring
